.flake8
.travis.yml
CHANGELOG.md
CODE_OF_CONDUCT.md
CONTRIBUTING.md
LICENSE
MANIFEST.in
README.rst
setup.cfg
setup.py
tox_install.py
docs/Makefile
docs/conf.py
docs/index.rst
docs/make.bat
docs/_build/html/_images/moire.png
docs/_build/html/_static/comment-bright.png
docs/_build/html/_static/comment-close.png
docs/_build/html/_static/comment.png
docs/_build/html/_static/down-pressed.png
docs/_build/html/_static/down.png
docs/_build/html/_static/file.png
docs/_build/html/_static/minus.png
docs/_build/html/_static/plus.png
docs/_build/html/_static/up-pressed.png
docs/_build/html/_static/up.png
docs/_build/html/_static/img/moire.png
docs/_static/img/moire.png
docs/api/moire.rst
docs/api/moire.widgets.rst
docs/manual/installation.rst
docs/manual/tutorial.rst
examples/__init__.py
examples/noisetv.py
moire/__init__.py
moire/main.py
moire.egg-info/PKG-INFO
moire.egg-info/SOURCES.txt
moire.egg-info/dependency_links.txt
moire.egg-info/requires.txt
moire.egg-info/top_level.txt
moire/assets/fonts/Xolonium Bold.ttf
moire/assets/fonts/Xolonium Regular.ttf
moire/widgets/__init__.py
moire/widgets/dlist.py
moire/widgets/panel.py
moire/widgets/sysinfo.py
requirements/main.txt