Metadata-Version: 2.1
Name: moire
Version: 0.1.0
Summary: Multi-Objective Interactive Runtime Environment
Home-page: https://github.com/a5kin/moire
Author: Andrey Zamaraev
Author-email: a5kin@github.com
License: MIT
Keywords: gui interactive environment simulation visualization
Platform: UNKNOWN
Classifier: Development Status :: 2 - Pre-Alpha
Classifier: Environment :: Console
Classifier: Intended Audience :: Developers
Classifier: Topic :: Games/Entertainment :: Simulation
Classifier: Topic :: Scientific/Engineering :: Visualization
Classifier: Topic :: Software Development :: Libraries
Classifier: Topic :: Artistic Software
Classifier: License :: OSI Approved :: MIT License
Classifier: Programming Language :: Python :: 3.5
Classifier: Programming Language :: Python :: 3.6
Classifier: Programming Language :: Python :: Implementation :: PyPy
Provides-Extra: dev
Provides-Extra: test
